hotel_manage_soumya/__init__.py
hotel_manage_soumya/booking.py
hotel_manage_soumya/room.py
hotel_manage_soumya/user.py
hotel_manage_soumya-0.0.6.dist-info/METADATA
hotel_manage_soumya-0.0.6.dist-info/WHEEL
hotel_manage_soumya-0.0.6.dist-info/licenses/LICENSE
hotel_manage_soumya-0.0.6.dist-info/RECORD
